geosss/__init__.py
geosss/distributions.py
geosss/io.py
geosss/mcmc.py
geosss/pointcloud.py
geosss/rand.py
geosss/registration.py
geosss/sphere.py
geosss/sphere_tesselation.py
geosss/spherical_curve.py
geosss/tsp_solver.py
geosss/utils.py
geosss-0.3.5.dist-info/LICENSE
geosss-0.3.5.dist-info/METADATA
geosss-0.3.5.dist-info/WHEEL
geosss-0.3.5.dist-info/RECORD
