Metadata-Version: 2.3
Name: geosss
Version: 0.3.5
Summary: Python package implementing an ideal and shrinkage-based geodesic slice sampling on the sphere.
License: BSD-3-Clause
Author: Michael Habeck
Author-email: michael.habeck@uni-jena.de
Requires-Python: >=3.10,<3.13
Classifier: License :: OSI Approved :: BSD License
Classifier: Programming Language :: Python :: 3
Classifier: Programming Language :: Python :: 3.10
Classifier: Programming Language :: Python :: 3.11
Classifier: Programming Language :: Python :: 3.12
Provides-Extra: dev
Requires-Dist: arviz (>=0.20.0,<0.21.0)
Requires-Dist: black (>=24.3.0,<25.0.0) ; extra == "dev"
Requires-Dist: corner (>=2.2.2,<3.0.0) ; extra == "dev"
Requires-Dist: ipykernel (>=6.25.0,<7.0.0) ; extra == "dev"
Requires-Dist: joblib (>=1.4.2,<2.0.0) ; extra == "dev"
Requires-Dist: matplotlib (>=3.7.2,<4.0.0) ; extra == "dev"
Requires-Dist: numpy (>=2.0.0,<3.0.0)
Requires-Dist: scipy (>=1.11.1,<2.0.0)
Requires-Dist: seaborn (>=0.12.2,<0.13.0) ; extra == "dev"
Project-URL: Repository, https://github.com/microscopic-image-analysis/geosss
